vit_pytorch/__init__.py
vit_pytorch/accept_video_wrapper.py
vit_pytorch/ats_vit.py
vit_pytorch/cait.py
vit_pytorch/cct.py
vit_pytorch/cct_3d.py
vit_pytorch/cross_vit.py
vit_pytorch/crossformer.py
vit_pytorch/cvt.py
vit_pytorch/deepvit.py
vit_pytorch/dino.py
vit_pytorch/distill.py
vit_pytorch/efficient.py
vit_pytorch/es_vit.py
vit_pytorch/extractor.py
vit_pytorch/jumbo_vit.py
vit_pytorch/learnable_memory_vit.py
vit_pytorch/levit.py
vit_pytorch/local_vit.py
vit_pytorch/look_vit.py
vit_pytorch/mae.py
vit_pytorch/max_vit.py
vit_pytorch/max_vit_with_registers.py
vit_pytorch/mobile_vit.py
vit_pytorch/mp3.py
vit_pytorch/mpp.py
vit_pytorch/na_vit.py
vit_pytorch/na_vit_nested_tensor.py
vit_pytorch/na_vit_nested_tensor_3d.py
vit_pytorch/nest.py
vit_pytorch/normalized_vit.py
vit_pytorch/parallel_vit.py
vit_pytorch/pit.py
vit_pytorch/recorder.py
vit_pytorch/regionvit.py
vit_pytorch/rvt.py
vit_pytorch/scalable_vit.py
vit_pytorch/sep_vit.py
vit_pytorch/simmim.py
vit_pytorch/simple_flash_attn_vit.py
vit_pytorch/simple_flash_attn_vit_3d.py
vit_pytorch/simple_uvit.py
vit_pytorch/simple_vit.py
vit_pytorch/simple_vit_1d.py
vit_pytorch/simple_vit_3d.py
vit_pytorch/simple_vit_with_fft.py
vit_pytorch/simple_vit_with_hyper_connections.py
vit_pytorch/simple_vit_with_patch_dropout.py
vit_pytorch/simple_vit_with_qk_norm.py
vit_pytorch/simple_vit_with_register_tokens.py
vit_pytorch/simple_vit_with_value_residual.py
vit_pytorch/t2t.py
vit_pytorch/twins_svt.py
vit_pytorch/vaat.py
vit_pytorch/vat.py
vit_pytorch/vat_siglip.py
vit_pytorch/vit.py
vit_pytorch/vit_1d.py
vit_pytorch/vit_3d.py
vit_pytorch/vit_for_small_dataset.py
vit_pytorch/vit_nd.py
vit_pytorch/vit_nd_pope.py
vit_pytorch/vit_nd_rotary.py
vit_pytorch/vit_with_decorr.py
vit_pytorch/vit_with_patch_dropout.py
vit_pytorch/vit_with_patch_merger.py
vit_pytorch/vivit.py
vit_pytorch/xcit.py
vit_pytorch-1.17.5.dist-info/licenses/LICENSE
vit_pytorch-1.17.5.dist-info/METADATA
vit_pytorch-1.17.5.dist-info/WHEEL
vit_pytorch-1.17.5.dist-info/top_level.txt
vit_pytorch-1.17.5.dist-info/RECORD
