Metadata-Version: 2.4
Name: vit-pytorch
Version: 1.17.5
Summary: Vision Transformer (ViT) - Pytorch
Author-email: Phil Wang <lucidrains@gmail.com>
License: MIT License
Project-URL: Homepage, https://github.com/lucidrains/vit-pytorch
Project-URL: Repository, https://github.com/lucidrains/vit-pytorch
Keywords: artificial intelligence,attention mechanism,image recognition
Classifier: Development Status :: 4 - Beta
Classifier: Intended Audience :: Developers
Classifier: Topic :: Scientific/Engineering :: Artificial Intelligence
Classifier: License :: OSI Approved :: MIT License
Classifier: Programming Language :: Python :: 3
Classifier: Programming Language :: Python :: 3 :: Only
Classifier: Programming Language :: Python :: 3.8
Classifier: Programming Language :: Python :: 3.9
Classifier: Programming Language :: Python :: 3.10
Classifier: Programming Language :: Python :: 3.11
Classifier: Programming Language :: Python :: 3.12
Requires-Python: >=3.8
License-File: LICENSE
Requires-Dist: einops>=0.7.0
Requires-Dist: torch>=1.10
Requires-Dist: torchvision
Provides-Extra: test
Requires-Dist: pytest; extra == "test"
Requires-Dist: torch==2.4.0; extra == "test"
Requires-Dist: torchvision==0.19.0; extra == "test"
Dynamic: license-file
